easy_id/__init__.py
easy_id/easy_id.py
easy_id/generators/__init__.py
easy_id/generators/base.py
easy_id/generators/nanoid.py
easy_id/generators/snowflake.py
easy_id/generators/ulid.py
easy_id-1.0.3.dist-info/METADATA
easy_id-1.0.3.dist-info/WHEEL
easy_id-1.0.3.dist-info/top_level.txt
easy_id-1.0.3.dist-info/RECORD
