Metadata-Version: 2.1
Name: easy_id
Version: 1.0.3
Summary: An easy to use suite of configurable id generators
Home-page: https://github.com/RadenTheFolf/easy_id
Author: RadenTheFolf
Author-email: raden@zynosstudios.com
Classifier: Programming Language :: Python :: 3
Classifier: Operating System :: OS Independent
